starvote/__init__.py
starvote/__main__.py
starvote/reference.py
starvote-2.1.6.dist-info/LICENSE
starvote-2.1.6.dist-info/WHEEL
starvote-2.1.6.dist-info/METADATA
starvote-2.1.6.dist-info/RECORD
