Metadata-Version: 2.1
Name: starvote
Version: 2.1.6
Summary: An election tabulator for the STAR electoral system, and others
Author-email: Larry Hastings <larry@hastings.org>
Requires-Python: >=3.6
Classifier: Intended Audience :: Developers
Classifier: License :: OSI Approved :: MIT License
Classifier: Programming Language :: Python :: 3
Classifier: Programming Language :: Python :: 3.6
Classifier: Programming Language :: Python :: 3.7
Classifier: Programming Language :: Python :: 3.8
Classifier: Programming Language :: Python :: 3.9
Classifier: Programming Language :: Python :: 3.10
Classifier: Programming Language :: Python :: 3.11
Classifier: Programming Language :: Python :: 3.12
Classifier: Programming Language :: Python :: 3.13
Requires-Dist: numpy ; extra == "reference"
Requires-Dist: pandas ; extra == "reference"
Project-URL: Source, https://github.com/larryhastings/starvote/
Provides-Extra: reference
